[
  {
    "title": "The Apple WWDC 2023 Keynote Live Blog (Starts at 10am PT/17:00 UTC)",
    "comment": "21",
    "author": "by Ryan Smith",
    "date": "6/5/2023"
  },
  {
    "title": "The Apple WWDC 2022 Keynote Live Blog (Starts at 10am PT/17:00 UTC)",
    "comment": "32",
    "author": "by Ryan Smith & Gavin Bshor",
    "date": "6/6/2022"
  },
  {
    "title": "The Apple \"Peek Performance\" Event Live Blog (Starts at 10am PT/18:00 UTC)",
    "comment": "79",
    "author": "by Ryan Smith",
    "date": "3/8/2022"
  },
  {
    "title": "The Apple 2021 Fall Mac Event Live Blog 10am PT (17:00 UTC)",
    "comment": "126",
    "author": "by Andrei Frumusanu",
    "date": "10/18/2021"
  },
  {
    "title": "The Keychron K3 Low Profile Wireless Mechanical Keyboard Review",
    "comment": "41",
    "author": "by E. Fylladitakis",
    "date": "7/13/2021"
  },
  {
    "title": "The Apple WWDC 2021 Keynote Live Blog (Starts at 10am PT/17:00 UTC)",
    "comment": "34",
    "author": "by Ryan Smith",
    "date": "6/7/2021"
  },
  {
    "title": "The 2020 Mac Mini Unleashed: Putting Apple Silicon M1 To The Test",
    "comment": "683",
    "author": "by Andrei Frumusanu",
    "date": "11/17/2020"
  },
  {
    "title": "Apple Intros First Three \u2018Apple Silicon\u2019 Macs: Late 2020 MacBook Air, 13-Inch MacBook Pro, & Mac Mini",
    "comment": "49",
    "author": "by Ryan Smith",
    "date": "11/10/2020"
  },
  {
    "title": "Apple Announces Event for November 10th: Arm-Based Macs Expected",
    "comment": "67",
    "author": "by Ryan Smith",
    "date": "11/2/2020"
  },
  {
    "title": "Apple Launches New 13\" MacBook Pro: 10th Gen Ice Lake and New Scissor Keyboard",
    "comment": "85",
    "author": "by Andrei Frumusanu",
    "date": "5/4/2020"
  },
  {
    "title": "Want a $50k Mac Pro Cheese Grater? Get a $60 PC Cheese Grater!",
    "comment": "60",
    "author": "by Dr. Ian Cutress",
    "date": "1/14/2020"
  },
  {
    "title": "Apple\u2019s Entry-Level 13-Inch MacBook Pro Gets Quad-Core CPU & Touch Bar",
    "comment": "40",
    "author": "by Ant Shilov",
    "date": "7/9/2019"
  },
  {
    "title": "The OWC Aura Pro X2 SSD Review: An NVMe Upgrade For Older Macs",
    "comment": "32",
    "author": "by Billy Tallis",
    "date": "6/5/2019"
  },
  {
    "title": "Apple Announces 2018 MacBook Air: Entry-Level Laptop Gets Essential Refresh",
    "comment": "75",
    "author": "by Ryan Smith",
    "date": "10/30/2018"
  },
  {
    "title": "Apple Updates MacBook Pro Family for 2018: More CPU Cores, DDR4, & Same Form Factors",
    "comment": "104",
    "author": "by Ryan Smith",
    "date": "7/12/2018"
  },
  {
    "title": "Bringing Vulkan to Apple's Platforms: Khronos Group Announces Open Source MoltenVK 1.0 & SDKs",
    "comment": "21",
    "author": "by Nate Oh",
    "date": "2/26/2018"
  },
  {
    "title": "Apple Announces Q1 FY 2018 Earnings",
    "comment": "13",
    "author": "by Brett Howse",
    "date": "2/1/2018"
  },
  {
    "title": "Apple Refreshes Mac Laptops: Pro, Vanilla, & Air All Get New CPUs",
    "comment": "53",
    "author": "by Ryan Smith",
    "date": "6/5/2017"
  },
  {
    "title": "Apple \"Hello Again\" 2016 Event Live Blog",
    "comment": "110",
    "author": "by Ryan Smith & Ian Cutress",
    "date": "10/27/2016"
  },
  {
    "title": "The Apple WWDC 2023 Keynote Live Blog (Starts at 10am PT/17:00 UTC)",
    "comment": "21",
    "author": "by Ryan Smith",
    "date": "6/5/2023"
  },
  {
    "title": "The Apple WWDC 2022 Keynote Live Blog (Starts at 10am PT/17:00 UTC)",
    "comment": "32",
    "author": "by Ryan Smith & Gavin Bshor",
    "date": "6/6/2022"
  },
  {
    "title": "The Apple \"Peek Performance\" Event Live Blog (Starts at 10am PT/18:00 UTC)",
    "comment": "79",
    "author": "by Ryan Smith",
    "date": "3/8/2022"
  },
  {
    "title": "The Apple 2021 Fall Mac Event Live Blog 10am PT (17:00 UTC)",
    "comment": "126",
    "author": "by Andrei Frumusanu",
    "date": "10/18/2021"
  },
  {
    "title": "The Keychron K3 Low Profile Wireless Mechanical Keyboard Review",
    "comment": "41",
    "author": "by E. Fylladitakis",
    "date": "7/13/2021"
  },
  {
    "title": "The Apple WWDC 2021 Keynote Live Blog (Starts at 10am PT/17:00 UTC)",
    "comment": "34",
    "author": "by Ryan Smith",
    "date": "6/7/2021"
  },
  {
    "title": "The 2020 Mac Mini Unleashed: Putting Apple Silicon M1 To The Test",
    "comment": "683",
    "author": "by Andrei Frumusanu",
    "date": "11/17/2020"
  },
  {
    "title": "Apple Intros First Three \u2018Apple Silicon\u2019 Macs: Late 2020 MacBook Air, 13-Inch MacBook Pro, & Mac Mini",
    "comment": "49",
    "author": "by Ryan Smith",
    "date": "11/10/2020"
  },
  {
    "title": "Apple Announces Event for November 10th: Arm-Based Macs Expected",
    "comment": "67",
    "author": "by Ryan Smith",
    "date": "11/2/2020"
  },
  {
    "title": "Apple Launches New 13\" MacBook Pro: 10th Gen Ice Lake and New Scissor Keyboard",
    "comment": "85",
    "author": "by Andrei Frumusanu",
    "date": "5/4/2020"
  },
  {
    "title": "Want a $50k Mac Pro Cheese Grater? Get a $60 PC Cheese Grater!",
    "comment": "60",
    "author": "by Dr. Ian Cutress",
    "date": "1/14/2020"
  },
  {
    "title": "Apple\u2019s Entry-Level 13-Inch MacBook Pro Gets Quad-Core CPU & Touch Bar",
    "comment": "40",
    "author": "by Ant Shilov",
    "date": "7/9/2019"
  },
  {
    "title": "The OWC Aura Pro X2 SSD Review: An NVMe Upgrade For Older Macs",
    "comment": "32",
    "author": "by Billy Tallis",
    "date": "6/5/2019"
  },
  {
    "title": "Apple Announces 2018 MacBook Air: Entry-Level Laptop Gets Essential Refresh",
    "comment": "75",
    "author": "by Ryan Smith",
    "date": "10/30/2018"
  },
  {
    "title": "Apple Updates MacBook Pro Family for 2018: More CPU Cores, DDR4, & Same Form Factors",
    "comment": "104",
    "author": "by Ryan Smith",
    "date": "7/12/2018"
  },
  {
    "title": "Bringing Vulkan to Apple's Platforms: Khronos Group Announces Open Source MoltenVK 1.0 & SDKs",
    "comment": "21",
    "author": "by Nate Oh",
    "date": "2/26/2018"
  },
  {
    "title": "Apple Announces Q1 FY 2018 Earnings",
    "comment": "13",
    "author": "by Brett Howse",
    "date": "2/1/2018"
  },
  {
    "title": "Apple Refreshes Mac Laptops: Pro, Vanilla, & Air All Get New CPUs",
    "comment": "53",
    "author": "by Ryan Smith",
    "date": "6/5/2017"
  },
  {
    "title": "Apple \"Hello Again\" 2016 Event Live Blog",
    "comment": "110",
    "author": "by Ryan Smith & Ian Cutress",
    "date": "10/27/2016"
  },
  {
    "title": "A First Look At Apple's macOS Sierra",
    "comment": "81",
    "author": "by Brand Chester",
    "date": "7/13/2016"
  },
  {
    "title": "Apple Opens The macOS Sierra Public Beta",
    "comment": "15",
    "author": "by Brand Chester",
    "date": "7/7/2016"
  },
  {
    "title": "Apple Announces macOS Sierra: Siri, Better iOS Convergence, New Metal Features, & More",
    "comment": "32",
    "author": "by Ryan Smith",
    "date": "6/14/2016"
  },
  {
    "title": "Apple Announces Q2 Fiscal Year 2016 Results: iPhone Sales Slowed But Services Gain",
    "comment": "41",
    "author": "by Brett Howse",
    "date": "4/26/2016"
  },
  {
    "title": "Apple Recalls \"Duckhead\" Power Adapters for Select Mac Laptops and iPads",
    "comment": "25",
    "author": "by Ant Shilov",
    "date": "1/28/2016"
  },
  {
    "title": "Apple Reports Q1 FY 2016 Results: Record Revenue Despite Flat iPhone Sales",
    "comment": "18",
    "author": "by Brett Howse",
    "date": "1/26/2016"
  },
  {
    "title": "Apple Open Sources The Swift Programming Language",
    "comment": "70",
    "author": "by Brand Chester",
    "date": "12/3/2015"
  },
  {
    "title": "Apple FY 2015 Q4 Results: Record Fourth Quarter With 48 Million iPhones Sold",
    "comment": "44",
    "author": "by Brett Howse",
    "date": "10/27/2015"
  },
  {
    "title": "Apple Updates The iMac Line With a 21.5\" Retina Model",
    "comment": "46",
    "author": "by Brand Chester",
    "date": "10/13/2015"
  },
  {
    "title": "Apple Announces Release Dates for iOS 9, watchOS 2, and OS X El Capitan",
    "comment": "7",
    "author": "by Brand Chester",
    "date": "9/9/2015"
  },
  {
    "title": "Apple Reports Q3 FY 2015 Results: Record Results With Strong iPhone And Mac Sales",
    "comment": "83",
    "author": "by Brett Howse",
    "date": "7/21/2015"
  },
  {
    "title": "A First Look At Apple's OS X El Capitan",
    "comment": "100",
    "author": "by Ryan Smith",
    "date": "6/15/2015"
  },
  {
    "title": "NVIDIA Acquires Game Porting Group & Tech From Transgaming",
    "comment": "56",
    "author": "by Ryan Smith",
    "date": "6/13/2015"
  },
  {
    "title": "Apple\u2019s Metal API Comes to OS X Desktops",
    "comment": "63",
    "author": "by Ryan Smith",
    "date": "6/10/2015"
  },
  {
    "title": "Apple Announces OS X El Capitan",
    "comment": "45",
    "author": "by Brand Chester",
    "date": "6/8/2015"
  },
  {
    "title": "Apple WWDC 2015 Keynote Liveblog",
    "comment": "15",
    "author": "by Ryan Smith & Brand Chester",
    "date": "6/8/2015"
  },
  {
    "title": "2015 15-inch Retina MacBook Pro\u2019s dGPU (R9 M370X) Is Cape Verde",
    "comment": "109",
    "author": "by Ryan Smith",
    "date": "5/23/2015"
  },
  {
    "title": "Apple Announces 2015 15\u201d Retina MacBook Pro, Cheaper 27\u201d Retina iMac",
    "comment": "75",
    "author": "by Ryan Smith",
    "date": "5/19/2015"
  },
  {
    "title": "Apple Releases FY 2015 Q2 Earnings Results: Strong Growth In China Fuel Large Sales",
    "comment": "67",
    "author": "by Brett Howse",
    "date": "4/27/2015"
  },
  {
    "title": "The 2015 MacBook Review",
    "comment": "354",
    "author": "by Ryan Smith",
    "date": "4/14/2015"
  },
  {
    "title": "Apple MacBook (2015) Hands-On",
    "comment": "217",
    "author": "by Ryan Smith",
    "date": "3/12/2015"
  },
  {
    "title": "A Look At OS X Yosemite And iOS 8.1",
    "comment": "173",
    "author": "by Brand Chester",
    "date": "10/27/2014"
  },
  {
    "title": "Apple Q4 FY 2014 Fiscal Results - 21% Mac Growth And Strong iPhone Sales",
    "comment": "38",
    "author": "by Brett Howse",
    "date": "10/20/2014"
  },
  {
    "title": "Hands On: Apple's iMac with Retina Display",
    "comment": "84",
    "author": "by Ryan Smith",
    "date": "10/16/2014"
  },
  {
    "title": "Apple Q3 2014 Fiscal Results Analysis",
    "comment": "12",
    "author": "by Brett Howse",
    "date": "7/22/2014"
  },
  {
    "title": "Apple Introduces New Entry Level iMac Priced at $1099",
    "comment": "64",
    "author": "by Brand Chester",
    "date": "6/18/2014"
  },
  {
    "title": "Computex 2014: Transcend Shows SSD370 with Custom Firmware, SSD & RAM Upgrade Kits for Macs",
    "comment": "5",
    "author": "by Kristian V\u00e4tt\u00f6",
    "date": "6/11/2014"
  },
  {
    "title": "Apple WWDC 2014 Live Blog",
    "comment": "44",
    "author": "by Anand Lal Shimpi",
    "date": "6/2/2014"
  },
  {
    "title": "Averting Disaster - A Guide To Computer Backups (2014)",
    "comment": "133",
    "author": "by Brett Howse",
    "date": "5/21/2014"
  },
  {
    "title": "Testing Improved 4K Display Support in OS X 10.9.3",
    "comment": "72",
    "author": "by Brand Chester & Anand Lal Shimpi",
    "date": "5/15/2014"
  },
  {
    "title": "Running an NVIDIA GTX 780 Ti Over Thunderbolt 2",
    "comment": "72",
    "author": "by Kristian V\u00e4tt\u00f6",
    "date": "5/4/2014"
  },
  {
    "title": "Apple Updates MacBook Air for 2014: Faster Haswell Parts & $100 Price Drop",
    "comment": "49",
    "author": "by Anand Lal Shimpi",
    "date": "4/29/2014"
  },
  {
    "title": "Apple Q2 2014 Fiscal Results",
    "comment": "27",
    "author": "by Brett Howse",
    "date": "4/23/2014"
  },
  {
    "title": "Spotify Introduces a Major Cross Platform UI Overhaul",
    "comment": "8",
    "author": "by Saumitra Bhagwat",
    "date": "4/2/2014"
  },
  {
    "title": "Improving the State of 4K Display Support Under OS X",
    "comment": "32",
    "author": "by Anand Lal Shimpi",
    "date": "3/7/2014"
  },
  {
    "title": "OWC to Bring Aftermarket SF3700 PCIe SSD Upgrades to 2013 Macs",
    "comment": "24",
    "author": "by Anand Lal Shimpi",
    "date": "1/10/2014"
  },
  {
    "title": "The Mac Pro Review (Late 2013)",
    "comment": "267",
    "author": "by Anand Lal Shimpi",
    "date": "12/31/2013"
  },
  {
    "title": "Apple Event (October 2013) - Live Blog",
    "comment": "101",
    "author": "by Anand Lal Shimpi & Brian Klug",
    "date": "10/22/2013"
  },
  {
    "title": "21.5-inch iMac (Late 2013) Review: Iris Pro Driving an Accurate Display",
    "comment": "127",
    "author": "by Anand Lal Shimpi",
    "date": "10/7/2013"
  },
  {
    "title": "The 2013 MacBook Air Review (11-inch)",
    "comment": "139",
    "author": "by Vivek Gowri",
    "date": "8/9/2013"
  },
  {
    "title": "Is Haswell Ready for Tablet Duty? Battery Life of Haswell ULT vs Modern ARM Tablets",
    "comment": "83",
    "author": "by Anand Lal Shimpi",
    "date": "7/22/2013"
  },
  {
    "title": "The 2013 MacBook Air: Core i5-4250U vs. Core i7-4650U",
    "comment": "129",
    "author": "by Anand Lal Shimpi",
    "date": "7/4/2013"
  },
  {
    "title": "Best Mac Laptops - June 2013",
    "comment": "74",
    "author": "by Anand Lal Shimpi",
    "date": "6/24/2013"
  },
  {
    "title": "The 2013 MacBook Air Review (13-inch)",
    "comment": "234",
    "author": "by Anand Lal Shimpi",
    "date": "6/24/2013"
  },
  {
    "title": "2013 MacBook Air: PCIe SSD and Haswell ULT Inside",
    "comment": "175",
    "author": "by Anand Lal Shimpi",
    "date": "6/10/2013"
  },
  {
    "title": "Up Close with the New Mac Pro",
    "comment": "137",
    "author": "by Anand Lal Shimpi",
    "date": "6/10/2013"
  },
  {
    "title": "WWDC 2013 Keynote Live Blog",
    "comment": "29",
    "author": "by Anand Lal Shimpi & Brian Klug",
    "date": "6/10/2013"
  },
  {
    "title": "Apple Cuts Pricing on MacBook Pro with Retina Display and SSD Upgrades",
    "comment": "37",
    "author": "by Anand Lal Shimpi",
    "date": "2/13/2013"
  },
  {
    "title": "Apple Is Now Using SanDisk SSDs in the Retina MacBook Pro As Well",
    "comment": "31",
    "author": "by Kristian V\u00e4tt\u00f6",
    "date": "2/5/2013"
  },
  {
    "title": "A Month with Apple's Fusion Drive",
    "comment": "127",
    "author": "by Anand Lal Shimpi",
    "date": "1/18/2013"
  },
  {
    "title": "Latest WebKit Build Doubles Scrolling Performance on MacBook Pro with Retina Display",
    "comment": "15",
    "author": "by Anand Lal Shimpi",
    "date": "12/4/2012"
  },
  {
    "title": "13-inch Retina MacBook Pro Review (Late 2012)",
    "comment": "80",
    "author": "by Anand Lal Shimpi",
    "date": "11/13/2012"
  },
  {
    "title": "The AnandTech Podcast: Episode 9",
    "comment": "49",
    "author": "by Anand Lal Shimpi",
    "date": "11/7/2012"
  },
  {
    "title": "Understanding Apple's Fusion Drive",
    "comment": "87",
    "author": "by Anand Lal Shimpi",
    "date": "10/24/2012"
  },
  {
    "title": "Up Close with the New 27-inch iMac's User Serviceable Memory Panel",
    "comment": "23",
    "author": "by Anand Lal Shimpi",
    "date": "10/23/2012"
  },
  {
    "title": "13-inch MacBook Pro with Retina Display: Hands On",
    "comment": "24",
    "author": "by Anand Lal Shimpi",
    "date": "10/23/2012"
  },
  {
    "title": "Office for Mac 2011 Gets Retina Display Support",
    "comment": "11",
    "author": "by Saumitra Bhagwat",
    "date": "9/19/2012"
  },
  {
    "title": "Western Digital My Book VelociRaptor Duo Review",
    "comment": "30",
    "author": "by Anand Lal Shimpi",
    "date": "8/30/2012"
  },
  {
    "title": "The AnandTech Podcast: Episode 2",
    "comment": "25",
    "author": "by Anand Lal Shimpi",
    "date": "8/28/2012"
  },
  {
    "title": "OWC Announces 480GB SSD Upgrade for MacBook Pro with Retina Display",
    "comment": "12",
    "author": "by Anand Lal Shimpi",
    "date": "8/14/2012"
  },
  {
    "title": "The 2012 MacBook Pro Review",
    "comment": "132",
    "author": "by Vivek Gowri",
    "date": "7/18/2012"
  },
  {
    "title": "The 2012 MacBook Air (11 & 13-inch) Review",
    "comment": "190",
    "author": "by Anand Lal Shimpi",
    "date": "7/16/2012"
  },
  {
    "title": "The next-gen MacBook Pro with Retina Display Review",
    "comment": "471",
    "author": "by Anand Lal Shimpi",
    "date": "6/23/2012"
  },
  {
    "title": "Windows 8 on the Retina Display MacBook Pro",
    "comment": "81",
    "author": "by Anand Lal Shimpi",
    "date": "6/14/2012"
  },
  {
    "title": "The next-gen MacBook Pro with Retina Display: SSD Analysis",
    "comment": "19",
    "author": "by Anand Lal Shimpi",
    "date": "6/13/2012"
  },
  {
    "title": "Chrome Canary Fixes Rendering Issue with Retina MacBook Pro",
    "comment": "11",
    "author": "by Anand Lal Shimpi",
    "date": "6/12/2012"
  },
  {
    "title": "Apple Confirms Email to Mac Pro User About Something Really Great in 2013",
    "comment": "21",
    "author": "by Anand Lal Shimpi",
    "date": "6/12/2012"
  },
  {
    "title": "MacBook Pro Retina Display Analysis",
    "comment": "188",
    "author": "by Anand Lal Shimpi",
    "date": "6/12/2012"
  },
  {
    "title": "SSD and USB 3.0 Performance of the Retina Display MacBook Pro",
    "comment": "33",
    "author": "by Anand Lal Shimpi",
    "date": "6/11/2012"
  },
  {
    "title": "How the Retina Display MacBook Pro Handles Scaling",
    "comment": "74",
    "author": "by Anand Lal Shimpi",
    "date": "6/11/2012"
  },
  {
    "title": "First Shots of the MacBook Pro with Retina Display, Updated: Even More Pics",
    "comment": "20",
    "author": "by Anand Lal Shimpi",
    "date": "6/11/2012"
  },
  {
    "title": "Mountain Lion Shipping in July, $19.99 for upgrades from Snow Leopard and Lion",
    "comment": "6",
    "author": "by Anand Lal Shimpi",
    "date": "6/11/2012"
  },
  {
    "title": "Mountain Lion Power Nap: Connected Standby",
    "comment": "3",
    "author": "by Anand Lal Shimpi",
    "date": "6/11/2012"
  },
  {
    "title": "Mountain Lion Safari Supports iCloud Tabs, Safari Tabs From all iOS and OS X Devices",
    "comment": "3",
    "author": "by Anand Lal Shimpi",
    "date": "6/11/2012"
  },
  {
    "title": "MacBook Pro with Retina Display Starts at $2199, Shipping Today",
    "comment": "35",
    "author": "by Anand Lal Shimpi",
    "date": "6/11/2012"
  },
  {
    "title": "The next-generation MacBook Pro: Ports",
    "comment": "10",
    "author": "by Anand Lal Shimpi",
    "date": "6/11/2012"
  },
  {
    "title": "Inside the next generation MacBook Pro",
    "comment": "4",
    "author": "by Anand Lal Shimpi",
    "date": "6/11/2012"
  },
  {
    "title": "This is the next generation MacBook Pro",
    "comment": "39",
    "author": "by Anand Lal Shimpi",
    "date": "6/11/2012"
  },
  {
    "title": "Apple's Updated MacBook Pro: Ivy Bridge and Kepler",
    "comment": "0",
    "author": "by Anand Lal Shimpi",
    "date": "6/11/2012"
  },
  {
    "title": "Apple Updates MacBook Air: Ivy Bridge, Up to 8GB of RAM, USB 3.0, 512GB SSD",
    "comment": "5",
    "author": "by Anand Lal Shimpi",
    "date": "6/11/2012"
  },
  {
    "title": "WWDC 2012: App Store Facts",
    "comment": "28",
    "author": "by Anand Lal Shimpi",
    "date": "6/11/2012"
  },
  {
    "title": "ASUS' Zenbook SSD and Apple's MacBook Air SSD Are Not Compatible",
    "comment": "22",
    "author": "by Anand Lal Shimpi",
    "date": "5/23/2012"
  },
  {
    "title": "OWC Releases Mercury Accelsior PCIe SSD",
    "comment": "33",
    "author": "by Kristian V\u00e4tt\u00f6",
    "date": "4/18/2012"
  },
  {
    "title": "Apple: 1080p Apple TV uses a Single-Core A5 SoC",
    "comment": "19",
    "author": "by Anand Lal Shimpi",
    "date": "3/7/2012"
  },
  {
    "title": "LaCie 2big Thunderbolt Series Review",
    "comment": "34",
    "author": "by Anand Lal Shimpi",
    "date": "2/25/2012"
  },
  {
    "title": "Thoughts on the Mac OS X Mountain Lion Developer Preview",
    "comment": "96",
    "author": "by Andrew Cunningham & Anand Lal Shimpi",
    "date": "2/19/2012"
  },
  {
    "title": "Apple Releases OS X 10.8 \"Mountain Lion\" Preview",
    "comment": "38",
    "author": "by Andrew Cunningham",
    "date": "2/16/2012"
  },
  {
    "title": "LaCie 2big Thunderbolt Series Now Available",
    "comment": "23",
    "author": "by Kristian V\u00e4tt\u00f6",
    "date": "2/15/2012"
  },
  {
    "title": "Apple Updates Final Cut Pro X, Brings Back Features from Final Cut Pro 7",
    "comment": "12",
    "author": "by Kristian V\u00e4tt\u00f6",
    "date": "1/31/2012"
  },
  {
    "title": "TRIM Enabler 2.0 for OS X Lion Released",
    "comment": "32",
    "author": "by Kristian V\u00e4tt\u00f6",
    "date": "1/22/2012"
  },
  {
    "title": "Sumitomo Electric's Thunderbolt Cable",
    "comment": "13",
    "author": "by Anand Lal Shimpi",
    "date": "1/13/2012"
  },
  {
    "title": "Seagate's GoFlex Thunderbolt Adapters",
    "comment": "17",
    "author": "by Anand Lal Shimpi",
    "date": "1/10/2012"
  },
  {
    "title": "MSI's GUS II: External GPU via Thunderbolt",
    "comment": "47",
    "author": "by Anand Lal Shimpi",
    "date": "1/9/2012"
  },
  {
    "title": "OCZ's Portable Thunderbolt SSD: Lightfoot",
    "comment": "12",
    "author": "by Anand Lal Shimpi",
    "date": "1/9/2012"
  },
  {
    "title": "OWC Mercury Aura Pro Express 6G 480GB SSD Upgrade for MacBook Air",
    "comment": "5",
    "author": "by Anand Lal Shimpi",
    "date": "1/8/2012"
  },
  {
    "title": "LaCie at CES: 2big & eSATA Thunderbolt Hubs",
    "comment": "2",
    "author": "by Anand Lal Shimpi",
    "date": "1/8/2012"
  },
  {
    "title": "Apple 15-inch MacBook Pro (Late 2011) Review",
    "comment": "106",
    "author": "by Anand Lal Shimpi",
    "date": "11/17/2011"
  },
  {
    "title": "iTunes Match Goes Live",
    "comment": "14",
    "author": "by Kristian V\u00e4tt\u00f6",
    "date": "11/14/2011"
  },
  {
    "title": "OWC Mercury Aura Pro Express 6G Review: A Fast MacBook Air SSD Upgrade",
    "comment": "40",
    "author": "by Anand Lal Shimpi",
    "date": "11/9/2011"
  },
  {
    "title": "LaCie Little Big Disk (240GB SSD) Review",
    "comment": "24",
    "author": "by Anand Lal Shimpi",
    "date": "11/8/2011"
  },
  {
    "title": "LaCie Little Big Disk (2TB) Review: More Affordable Thunderbolt Storage",
    "comment": "40",
    "author": "by Anand Lal Shimpi",
    "date": "10/31/2011"
  },
  {
    "title": "The Apple Thunderbolt Display Review",
    "comment": "277",
    "author": "by Anand Lal Shimpi",
    "date": "9/23/2011"
  },
  {
    "title": "LaCie Brings (more) Affordable Thunderbolt Storage to Macs with Little Big Disk, Available in Retail",
    "comment": "17",
    "author": "by Anand Lal Shimpi",
    "date": "9/20/2011"
  },
  {
    "title": "OWC Releases 6Gb/s SSD Upgrades for 2011 MacBook Air",
    "comment": "8",
    "author": "by Kristian V\u00e4tt\u00f6",
    "date": "9/16/2011"
  },
  {
    "title": "Western Digital My Book Studio Edition II 6TB Review",
    "comment": "34",
    "author": "by Anand Lal Shimpi",
    "date": "9/10/2011"
  },
  {
    "title": "The Thunderbolt Devices Trickle In: Magma's ExpressBox 3T",
    "comment": "17",
    "author": "by Anand Lal Shimpi",
    "date": "9/7/2011"
  },
  {
    "title": "HighPoint Brings 4-port USB 3.0 to Mac Pro",
    "comment": "5",
    "author": "by Anand Lal Shimpi",
    "date": "8/25/2011"
  },
  {
    "title": "Airport Extreme (5th Gen) and Time Capsule (4th Gen) Review - Faster WiFi",
    "comment": "90",
    "author": "by Brian Klug",
    "date": "8/5/2011"
  },
  {
    "title": "In-Depth with Mac OS X Lion Server",
    "comment": "87",
    "author": "by Andrew Cunningham",
    "date": "8/2/2011"
  },
  {
    "title": "Apple's 11-inch MacBook Air (Core i7 1.8GHz) Review Update",
    "comment": "64",
    "author": "by Anand Lal Shimpi",
    "date": "8/1/2011"
  },
  {
    "title": "Eagle Ridge: The Cheaper, (optionally) Smaller Thunderbolt Controller",
    "comment": "20",
    "author": "by Anand Lal Shimpi",
    "date": "7/28/2011"
  },
  {
    "title": "The 2011 MacBook Air (11 & 13-inch): Thoroughly Reviewed",
    "comment": "115",
    "author": "by Anand Lal Shimpi",
    "date": "7/28/2011"
  },
  {
    "title": "2011 MacBook Air SSD Features the Same Controller as Samsung 470",
    "comment": "0",
    "author": "by Kristian V\u00e4tt\u00f6",
    "date": "7/27/2011"
  },
  {
    "title": "Apple Updates Cinema Display, It's a Thunderbolt Display Now",
    "comment": "94",
    "author": "by Kristian V\u00e4tt\u00f6",
    "date": "7/20/2011"
  },
  {
    "title": "2011 Mac Mini goes Sandy Bridge: Specs, details and our thoughts",
    "comment": "87",
    "author": "by Kristian V\u00e4tt\u00f6",
    "date": "7/20/2011"
  },
  {
    "title": "The 2011 MacBook Air: Specs and Details",
    "comment": "81",
    "author": "by Andrew Cunningham",
    "date": "7/20/2011"
  },
  {
    "title": "Back to the Mac: OS X 10.7 Lion Review",
    "comment": "112",
    "author": "by Andrew Cunningham, Kristian V\u00e4tt\u00f6 & Anand Lal Shimpi",
    "date": "7/20/2011"
  },
  {
    "title": "Promise Pegasus R6 & Mac Thunderbolt Review",
    "comment": "94",
    "author": "by Anand Lal Shimpi",
    "date": "7/8/2011"
  },
  {
    "title": "Apple Thunderbolt Cable & Promise Pegasus RAID System Available Now",
    "comment": "50",
    "author": "by Anand Lal Shimpi",
    "date": "6/28/2011"
  },
  {
    "title": "WWDC 2011: iCloud",
    "comment": "46",
    "author": "by Andrew Cunningham",
    "date": "6/6/2011"
  },
  {
    "title": "WWDC 2011: OS X 10.7 Lion",
    "comment": "50",
    "author": "by Andrew Cunningham",
    "date": "6/6/2011"
  },
  {
    "title": "Computex 2011: Some Time with Promise's Thunderbolt Devices",
    "comment": "8",
    "author": "by Anand Lal Shimpi",
    "date": "6/1/2011"
  },
  {
    "title": "The 27-inch Apple iMac Review (2011)",
    "comment": "140",
    "author": "by Anand Lal Shimpi",
    "date": "5/27/2011"
  },
  {
    "title": "Apple's iMac: The First Z68 for Sale?",
    "comment": "37",
    "author": "by Anand Lal Shimpi",
    "date": "5/4/2011"
  },
  {
    "title": "The New 2011 iMacs: Specs and Details",
    "comment": "106",
    "author": "by Andrew Cunningham",
    "date": "5/3/2011"
  },
  {
    "title": "Apple Now Using Samsung SSDs in MacBook Air?",
    "comment": "33",
    "author": "by Kristian V\u00e4tt\u00f6",
    "date": "4/15/2011"
  },
  {
    "title": "Sparrow: An OS X IMAP Client for Gmail Users",
    "comment": "22",
    "author": "by Andrew Cunningham",
    "date": "4/7/2011"
  },
  {
    "title": "The MacBook Pro Review (13 & 15-inch): 2011 Brings Sandy Bridge",
    "comment": "198",
    "author": "by Anand Lal Shimpi, Brian Klug & Vivek Gowri",
    "date": "3/10/2011"
  },
  {
    "title": "Apple's 11-inch Upgraded MacBook Air: Do 1.6GHz and 4GB Make a Difference?",
    "comment": "85",
    "author": "by Anand Lal Shimpi",
    "date": "11/6/2010"
  },
  {
    "title": "Apple's 2010 MacBook Air (11 & 13 inch) Thoroughly Reviewed",
    "comment": "186",
    "author": "by Anand Lal Shimpi",
    "date": "10/26/2010"
  },
  {
    "title": "Apple MacBook Pro 13: Can a Mac Be a Decent Windows Laptop?",
    "comment": "118",
    "author": "by Vivek Gowri",
    "date": "10/14/2010"
  },
  {
    "title": "Apple Mac Pro (Mid 2010) Review",
    "comment": "84",
    "author": "by Anand Lal Shimpi",
    "date": "10/6/2010"
  },
  {
    "title": "The Apple TV (2010) Review",
    "comment": "36",
    "author": "by Anand Lal Shimpi",
    "date": "10/4/2010"
  },
  {
    "title": "The Apple TV (2010): Dissected",
    "comment": "23",
    "author": "by Anand Lal Shimpi",
    "date": "9/29/2010"
  },
  {
    "title": "Apple 27-inch LED Cinema Display Review",
    "comment": "93",
    "author": "by Anand Lal Shimpi",
    "date": "9/28/2010"
  },
  {
    "title": "Apple Mac mini Review (Mid 2010)",
    "comment": "93",
    "author": "by Anand Lal Shimpi",
    "date": "8/9/2010"
  },
  {
    "title": "Apple's 13-inch MacBook Pro (Early 2010) Reviewed: Shaking the CPU/GPU Balance",
    "comment": "93",
    "author": "by Anand Lal Shimpi",
    "date": "6/9/2010"
  },
  {
    "title": "Mac OS X Steam Performance: Half Life 2 Episode 2, Still Slower than Windows",
    "comment": "97",
    "author": "by Anand Lal Shimpi",
    "date": "6/4/2010"
  },
  {
    "title": "Update: Mac OS X Portal Performance",
    "comment": "178",
    "author": "by Ryan Smith",
    "date": "5/13/2010"
  },
  {
    "title": "This Just In: Apple iPad 3G, Same Speed as iPhone 3GS over 3G?",
    "comment": "11",
    "author": "by Anand Lal Shimpi",
    "date": "4/30/2010"
  },
  {
    "title": "Adobe Enables Flash GPU Acceleration in OS X, We Test It",
    "comment": "38",
    "author": "by Anand Lal Shimpi",
    "date": "4/28/2010"
  },
  {
    "title": "Apple's 15-inch 2010 MacBook Pro: More Battery Life Tests, High Res Display Evaluated",
    "comment": "69",
    "author": "by Anand Lal Shimpi",
    "date": "4/24/2010"
  },
  {
    "title": "Apple's 15-inch Core i5 MacBook Pro: The One to Get?",
    "comment": "114",
    "author": "by Anand Lal Shimpi",
    "date": "4/14/2010"
  },
  {
    "title": "Apple's iPad - The AnandTech Review",
    "comment": "108",
    "author": "by Anand Lal Shimpi, Brian Klug & Vivek Gowri",
    "date": "4/7/2010"
  },
  {
    "title": "Done for 2009: The Holiday MacBook Pro Roundup",
    "comment": "115",
    "author": "by Anand Lal Shimpi",
    "date": "11/10/2009"
  },
  {
    "title": "Upgrading and Analyzing Apple's Nehalem Mac Pro",
    "comment": "58",
    "author": "by Anand Lal Shimpi",
    "date": "7/13/2009"
  },
  {
    "title": "The New MacBook Pro Part II: Lower Battery Life Under Vista & SATA Issues",
    "comment": "82",
    "author": "by Anand Lal Shimpi",
    "date": "6/15/2009"
  },
  {
    "title": "Apple's 2009 MacBook Pro: Battery Life to Die For",
    "comment": "113",
    "author": "by Anand Lal Shimpi",
    "date": "6/12/2009"
  },
  {
    "title": "Apple's Redesigned MacBook and MacBook Pro: Thoroughly Reviewed",
    "comment": "66",
    "author": "by Anand Lal Shimpi",
    "date": "10/22/2008"
  },
  {
    "title": "Apple's MacBook/MacBook Pro Redesign: A Discussion of Specifications",
    "comment": "35",
    "author": "by Anand Lal Shimpi & Manveer Wass",
    "date": "10/14/2008"
  },
  {
    "title": "Apple's MacBook Pro with 128GB SSD: Performance and Battery Life Investigated",
    "comment": "39",
    "author": "by Anand Lal Shimpi",
    "date": "4/15/2008"
  },
  {
    "title": "Apple\u2019s 45nm Refresh: New MacBook & MacBook Pro",
    "comment": "52",
    "author": "by Anand Lal Shimpi",
    "date": "2/29/2008"
  },
  {
    "title": "Apple's New Penryn MacBook Pro: Dissected",
    "comment": "18",
    "author": "by Anand Lal Shimpi",
    "date": "2/26/2008"
  },
  {
    "title": "The MacBook Air: Thoroughly Reviewed",
    "comment": "42",
    "author": "by Anand Lal Shimpi",
    "date": "2/13/2008"
  },
  {
    "title": "The Truth about MacBook Air Battery Life",
    "comment": "55",
    "author": "by Anand Lal Shimpi",
    "date": "2/7/2008"
  },
  {
    "title": "The Other Office: Microsoft Office 2008 for Mac Review",
    "comment": "13",
    "author": "by Ryan Smith",
    "date": "2/5/2008"
  },
  {
    "title": "Inside Apple's MacBook Air",
    "comment": "13",
    "author": "by Anand Lal Shimpi",
    "date": "2/4/2008"
  },
  {
    "title": "The MacBook Air CPU Mystery: More Details Revealed",
    "comment": "42",
    "author": "by Anand Lal Shimpi",
    "date": "1/17/2008"
  },
  {
    "title": "Apple's MacBook Air: Uncovering Intel's Custom CPU for Apple",
    "comment": "54",
    "author": "by Anand Lal Shimpi",
    "date": "1/15/2008"
  },
  {
    "title": "Apple TV - Part 2: Apple Enters the Digital Home",
    "comment": "48",
    "author": "by Anand Lal Shimpi",
    "date": "3/26/2007"
  },
  {
    "title": "Apple TV - Part 1: Unboxed and Dissected",
    "comment": "37",
    "author": "by Anand Lal Shimpi",
    "date": "3/22/2007"
  },
  {
    "title": "Apple's Mac Pro - Upgrading CPUs, Memory & Running XP",
    "comment": "72",
    "author": "by Anand Lal Shimpi",
    "date": "9/12/2006"
  },
  {
    "title": "Apple's Mac Pro - A True PowerMac Successor",
    "comment": "96",
    "author": "by Anand Lal Shimpi",
    "date": "8/16/2006"
  },
  {
    "title": "Apple's Mac Pro: A Discussion of Specifications",
    "comment": "33",
    "author": "by Anand Lal Shimpi",
    "date": "8/9/2006"
  },
  {
    "title": "Apple's MacBook Pro: Using it as a Mac and a PC",
    "comment": "52",
    "author": "by Anand Lal Shimpi",
    "date": "4/13/2006"
  },
  {
    "title": "Apple Makes the Switch: iMac G5 vs. iMac Core Duo",
    "comment": "36",
    "author": "by Anand Lal Shimpi",
    "date": "1/30/2006"
  },
  {
    "title": "No More Apple Mysteries, Part Two",
    "comment": "48",
    "author": "by Johan De Gelas",
    "date": "9/1/2005"
  },
  {
    "title": "ATI Radeon 9600 Pro Mac & PC Edition: One Card for All",
    "comment": "35",
    "author": "by Anand Lal Shimpi",
    "date": "8/19/2005"
  },
  {
    "title": "Apple's Mighty Mouse: The Move to Multi-Button",
    "comment": "45",
    "author": "by Anand Lal Shimpi",
    "date": "8/4/2005"
  },
  {
    "title": "No more mysteries: Apple's G5 versus x86, Mac OS X versus Linux",
    "comment": "116",
    "author": "by Johan De Gelas",
    "date": "6/3/2005"
  },
  {
    "title": "Mac OS X 10.4 Tiger Review",
    "comment": "55",
    "author": "by Anand Lal Shimpi",
    "date": "4/29/2005"
  },
  {
    "title": "Mac Memory Roundup Q1 2005 - In Search of Affordable Upgrades",
    "comment": "33",
    "author": "by Anand Lal Shimpi",
    "date": "3/1/2005"
  },
  {
    "title": "The Mac mini as a Media Computer",
    "comment": "39",
    "author": "by Anand Lal Shimpi",
    "date": "2/16/2005"
  },
  {
    "title": "Apple's Mac mini - Tempting PC Users Everywhere",
    "comment": "198",
    "author": "by Anand Lal Shimpi",
    "date": "1/25/2005"
  },
  {
    "title": "A Month with a Mac - Part II: The Mobile Experience",
    "comment": "60",
    "author": "by Anand Lal Shimpi",
    "date": "1/24/2005"
  },
  {
    "title": "ATI Radeon X800 XT Mac Edition: Competition in the Mac Market",
    "comment": "35",
    "author": "by Anand Lal Shimpi",
    "date": "1/5/2005"
  },
  {
    "title": "A Month with a Mac: A Die-Hard PC User's Perspective",
    "comment": "215",
    "author": "by Anand Lal Shimpi",
    "date": "10/8/2004"
  }
]